cs/mplutils.py
cs.mplutils-20230407.dist-info/METADATA
cs.mplutils-20230407.dist-info/WHEEL
cs.mplutils-20230407.dist-info/top_level.txt
cs.mplutils-20230407.dist-info/RECORD
