Metadata-Version: 2.1
Name: cs.mplutils
Version: 20230407
Summary: A few conveniences for working with matplotlib.
Home-page: https://bitbucket.org/cameron_simpson/css/commits/all
Author: Cameron Simpson
Author-email: Cameron Simpson <cs@cskk.id.au>
License: GNU General Public License v3 or later (GPLv3+)
Project-URL: URL, https://bitbucket.org/cameron_simpson/css/commits/all
Keywords: python3
Classifier: Development Status :: 3 - Alpha
Classifier: Programming Language :: Python :: 3
Classifier: Intended Audience :: Developers
Classifier: Operating System :: OS Independent
Classifier: Topic :: Software Development :: Libraries :: Python Modules
Classifier: License :: OSI Approved :: GNU General Public License v3 or later (GPLv3+)
Requires-Dist: cs.buffer (>=20230401)
Requires-Dist: cs.deco (>=20230331)
Requires-Dist: cs.lex (>=20230401)
Requires-Dist: cs.pfx (>=20230331)
Requires-Dist: matplotlib
Requires-Dist: typeguard
